Workbook

Sheet Itinerari
A1: # | B1: Ciutat / Zona | C1: Dia | D1: Lloc | E1: Categoria | F1: Prioritat | G1: Adreça | H1: Horari | I1: Durada | J1: Descripció | K1: Notes | L1: Google Maps | M1: Apple Maps | N1: Viquipèdia | O1: Visitat
A2: 1 | B2: Tòquio | C2: Dia 1 · Tokio modern, tradicional i neons | D2: Senso-ji / Kaminarimon | E2: Temples i santuaris | F2: - | G2: 2-3-1 Asakusa, Taito, Tokyo | H2: No indicat als arxius | I2: 1 h - 1 h 30 min | J2: Fundat l'any 645, és el temple budista més antic de Tòquio, dedicat a la deessa Kannon i un dels centres espirituals més visitats del Japó. S'hi accedeix per la icònica porta Kaminarimon amb el seu gran fanal vermell, seguida pel carrer comercial Nakamise-dori. | K2: Millor a primera hora o al vespre per evitar multituds. | L2: Obrir a Google Maps | M2: Obrir a Apple Maps | N2: Obrir article
A3: 2 | B3: Tòquio | C3: Dia 1 · Tokio modern, tradicional i neons | D3: Asakusa Culture Tourist Information Center | E3: Miradors | F3: - | G3: 2-18-9 Kaminarimon, Taito, Tokyo | H3: No indicat als arxius | I3: 20 - 30 min | J3: Edifici dissenyat per l'arquitecte Kengo Kuma que combina l'oficina d'informació turística d'Asakusa amb un mirador gratuït al vuitè pis, amb vistes de la porta Kaminarimon, el carrer Nakamise i, en dies clars, el Tokyo Skytree. | K3: Pujada ràpida i molt útil per situar Asakusa. | L3: Obrir a Google Maps | M3: Obrir a Apple Maps | N3: Cercar (sense article confirmat)
A4: 3 | B4: Tòquio | C4: Dia 1 · Tokio modern, tradicional i neons | D4: Kappabashi-dori | E4: Botigues | F4: - | G4: Kappabashi-dori, Taito, Tokyo | H4: No indicat als arxius | I4: 45 min - 1 h | J4: Conegut com el 'carrer de la cuina', Kappabashi-dori concentra centenars de botigues a l'engròs d'estris de cuina, ganivets i ceràmica, i és famós pels aliments de plàstic (sampuru) que decoren els aparadors dels restaurants japonesos. | K4: Molt recomanable si vols souvenirs pràctics de cuina japonesa. | L4: Obrir a Google Maps | M4: Obrir a Apple Maps | N4: Cercar (sense article confirmat)
A5: 4 | B5: Tòquio | C5: Dia 1 · Tokio modern, tradicional i neons | D5: Roppongi Hills / Mori Tower | E5: Miradors | F5: - | G5: Roppongi Hills, Minato, Tokyo | H5: No indicat als arxius | I5: 1 h 30 min | J5: Roppongi Hills és un dels grans complexos urbans de Tòquio (obert el 2003), amb la Mori Tower com a edifici central, el museu Mori Art Museum al pis 53 i el mirador Tokyo City View, un dels més ben valorats de la ciutat gràcies a les vistes de 360 graus. | K5: Reserva/consulta horaris si vols pujar al Tokyo City View. | L5: Obrir a Google Maps | M5: Obrir a Apple Maps | N5: Obrir article
A6: 5 | B6: Tòquio | C6: Dia 1 · Tokio modern, tradicional i neons | D6: The National Art Center, Tokyo | E6: Museus i cultura | F6: - | G6: 7-22-2 Roppongi, Minato, Tokyo | H6: No indicat als arxius | I6: 45 min - 1 h 30 min | J6: Obert el 2007 i dissenyat per l'arquitecte Kisho Kurokawa, és el museu més gran del Japó per superfície i, de manera peculiar, no té col·lecció permanent: només acull exposicions temporals. La façana ondulada de vidre és en si mateixa una atracció. | K6: Ideal si hi ha una exposició que t’interessi; si vas just de temps, fes només l’edifici. | L6: Obrir a Google Maps | M6: Obrir a Apple Maps | N6: Obrir article
A7: 6 | B7: Tòquio | C7: Dia 1 · Tokio modern, tradicional i neons | D7: Omotesando | E7: Monuments | F7: - | G7: Omotesando, Minato/Shibuya, Tokyo | H7: No indicat als arxius | I7: 45 min | J7: Avinguda arbrada sovint anomenada els 'Camps Elisis de Tòquio', coneguda per l'arquitectura d'autor de les botigues de moda de luxe dissenyades per arquitectes de renom internacional. | K7: Passeig curt per veure façanes i ambient. | L7: Obrir a Google Maps | M7: Obrir a Apple Maps | N7: Obrir article
A8: 7 | B8: Tòquio | C8: Dia 1 · Tokio modern, tradicional i neons | D8: Shibuya Sky | E8: Miradors | F8: - | G8: Shibuya Scramble Square, Shibuya, Tokyo | H8: No indicat als arxius | I8: 1 h - 1 h 30 min | J8: Mirador a l'aire lliure al capdamunt de la torre Shibuya Scramble Square (230 m), inaugurat el 2019. Ofereix vistes panoràmiques de 360 graus sobre Shibuya i, en dies clars, del mont Fuji; molt popular a la posta de sol. | K8: Reserva amb antelació, especialment per a la posta de sol. | L8: Obrir a Google Maps | M8: Obrir a Apple Maps | N8: Obrir article
A9: 8 | B9: Tòquio | C9: Dia 1 · Tokio modern, tradicional i neons | D9: Shibuya Scramble Crossing / Hachiko | E9: Miradors | F9: - | G9: Shibuya Station area, Tokyo | H9: No indicat als arxius | I9: 30 - 45 min | J9: Considerat el creuament de vianants més transitat del món, amb fins a nou direccions de pas simultànies. Al costat hi ha l'estàtua de Hachikō, el gos que va esperar fidelment el seu amo durant anys, convertit en símbol de lleialtat i punt de trobada. | K9: Bon lloc per començar la tarda a Shibuya. | L9: Obrir a Google Maps | M9: Obrir a Apple Maps | N9: Obrir article
A10: 9 | B10: Tòquio | C10: Dia 1 · Tokio modern, tradicional i neons | D10: Takeshita-dori / Harajuku | E10: Botigues | F10: - | G10: Takeshita Street, Jingumae, Shibuya, Tokyo | H10: No indicat als arxius | I10: 45 min - 1 h | J10: Carrer estret i atapeït considerat l'epicentre de la moda juvenil i les subcultures de Tòquio, amb botigues de roba alternativa, cosplay i dolços virals. Els carrers laterals ofereixen una experiència més tranquil·la que l'artèria principal. | K10: Els carrers laterals solen ser més agradables que l’artèria principal. | L10: Obrir a Google Maps | M10: Obrir a Apple Maps | N10: Obrir article
A11: 10 | B11: Tòquio | C11: Dia 1 · Tokio modern, tradicional i neons | D11: Meiji Jingu | E11: Temples i santuaris | F11: - | G11: 1-1 Yoyogikamizonocho, Shibuya, Tokyo | H11: No indicat als arxius | I11: 1 h | J11: Santuari xintoista dedicat a l'emperador Meiji i la seva esposa, inaugurat el 1920 i reconstruït després de la Segona Guerra Mundial. Envoltat per un bosc artificial de més de 100.000 arbres donats per tot el Japó, contrasta amb el bullici de Harajuku. | K11: Tanca relativament aviat; no el deixis per massa tard. | L11: Obrir a Google Maps | M11: Obrir a Apple Maps | N11: Obrir article
A12: 11 | B12: Tòquio | C12: Dia 1 · Tokio modern, tradicional i neons | D12: Tokyo Metropolitan Government Building | E12: Miradors | F12: - | G12: 2-8-1 Nishi-Shinjuku, Shinjuku, Tokyo | H12: No indicat als arxius | I12: 45 min - 1 h | J12: Seu del govern metropolità de Tòquio, dissenyada per Kenzo Tange i inaugurada el 1991. Les dues torres bessones alberguen miradors gratuïts a 202 metres d'alçada, una alternativa econòmica als miradors de pagament. | K12: Alternativa econòmica als miradors de pagament. | L12: Obrir a Google Maps | M12: Obrir a Apple Maps | N12: Obrir article
A13: 12 | B13: Tòquio | C13: Dia 1 · Tokio modern, tradicional i neons | D13: Omoide Yokocho | E13: Menjar | F13: - | G13: 1 Chome Nishishinjuku, Shinjuku, Tokyo | H13: No indicat als arxius | I13: 1 h - 1 h 30 min | J13: Xarxa de callejons estrets sorgits al mercat negre de la postguerra, plens de minúscules parades de yakitori i izakaya. El seu nom significa 'carreró dels records' i conserva l'atmosfera del Tòquio de mitjan segle XX. | K13: Bon punt per sopar; locals petits i ambient intens. | L13: Obrir a Google Maps | M13: Obrir a Apple Maps | N13: Obrir article
... A236: 235 | B236: Himeji | C236: Excursions opcionals · Mig dia fora del centre | D236: Nada no Kenka Matsuri | E236: Activitats | F236: Recomanat | G236: Santuari Matsubara Hachiman, Shirahama-cho, Himeji, Hyōgo | H236: 14 i 15 d'octubre (batalles principals: tarda del 14 i migdia del 15) | I236: Mig dia | J236: Considerat el festival de lluita més impressionant del Japó: diferents grups d'homes, gairebé en taparrabos, es baten amb els seus mikoshi (altars portàtils) al santuari Matsubara Hachiman per veure quin grup guanya. Hi corre el sake sense parar i no hi ha barreres clares entre participants i espectadors. | K236: Trieu bé des d'on mirar: hi ha zones tranquil·les i d'altres on és fàcil rebre algun cop accidental d'un participant. | L236: Obrir a Google Maps | M236: Obrir a Apple Maps | N236: Cercar (sense article confirmat)

Sheet Resum
A1: Resum per ciutat / zona
A2: Ciutat / Zona | B2: Nombre de llocs | C2: Visitats
A3: Tòquio | B3: =COUNTIF(Itinerari!$B$2:$B$236,A3) -> 38 | C3: =COUNTIFS(Itinerari!$B$2:$B$236,A3,Itinerari!$O$2:$O$236,"X") -> 0
A4: Kyoto | B4: =COUNTIF(Itinerari!$B$2:$B$236,A4) -> 40 | C4: =COUNTIFS(Itinerari!$B$2:$B$236,A4,Itinerari!$O$2:$O$236,"X") -> 0
A5: Osaka | B5: =COUNTIF(Itinerari!$B$2:$B$236,A5) -> 51 | C5: =COUNTIFS(Itinerari!$B$2:$B$236,A5,Itinerari!$O$2:$O$236,"X") -> 0
A6: Nikko | B6: =COUNTIF(Itinerari!$B$2:$B$236,A6) -> 14 | C6: =COUNTIFS(Itinerari!$B$2:$B$236,A6,Itinerari!$O$2:$O$236,"X") -> 0
A7: Kamakura | B7: =COUNTIF(Itinerari!$B$2:$B$236,A7) -> 17 | C7: =COUNTIFS(Itinerari!$B$2:$B$236,A7,Itinerari!$O$2:$O$236,"X") -> 0
A8: Hakone | B8: =COUNTIF(Itinerari!$B$2:$B$236,A8) -> 18 | C8: =COUNTIFS(Itinerari!$B$2:$B$236,A8,Itinerari!$O$2:$O$236,"X") -> 0
A9: Nara | B9: =COUNTIF(Itinerari!$B$2:$B$236,A9) -> 21 | C9: =COUNTIFS(Itinerari!$B$2:$B$236,A9,Itinerari!$O$2:$O$236,"X") -> 0
A10: Wakayama | B10: =COUNTIF(Itinerari!$B$2:$B$236,A10) -> 11 | C10: =COUNTIFS(Itinerari!$B$2:$B$236,A10,Itinerari!$O$2:$O$236,"X") -> 0
A11: Hiroshima | B11: =COUNTIF(Itinerari!$B$2:$B$236,A11) -> 16 | C11: =COUNTIFS(Itinerari!$B$2:$B$236,A11,Itinerari!$O$2:$O$236,"X") -> 0
A12: Himeji | B12: =COUNTIF(Itinerari!$B$2:$B$236,A12) -> 9 | C12: =COUNTIFS(Itinerari!$B$2:$B$236,A12,Itinerari!$O$2:$O$236,"X") -> 0
A14: TOTAL | B14: =SUM(B3:B12) -> 235 | C14: =SUM(C3:C12) -> 0
A16: Resum per categoria
A17: Categoria | B17: Nombre de llocs
A18: Temples i santuaris | B18: =COUNTIF(Itinerari!$E$2:$E$236,"*"&A18&"*") -> 71
A19: Miradors | B19: =COUNTIF(Itinerari!$E$2:$E$236,"*"&A19&"*") -> 25
A20: Museus i cultura | B20: =COUNTIF(Itinerari!$E$2:$E$236,"*"&A20&"*") -> 19
A21: Monuments | B21: =COUNTIF(Itinerari!$E$2:$E$236,"*"&A21&"*") -> 18
A22: Castells | B22: =COUNTIF(Itinerari!$E$2:$E$236,"*"&A22&"*") -> 1
A23: Natura i parcs | B23: =COUNTIF(Itinerari!$E$2:$E$236,"*"&A23&"*") -> 20
A24: Barris | B24: =COUNTIF(Itinerari!$E$2:$E$236,"*"&A24&"*") -> 20
A25: Menjar | B25: =COUNTIF(Itinerari!$E$2:$E$236,"*"&A25&"*") -> 24
A26: Botigues | B26: =COUNTIF(Itinerari!$E$2:$E$236,"*"&A26&"*") -> 21
A27: Activitats | B27: =COUNTIF(Itinerari!$E$2:$E$236,"*"&A27&"*") -> 21
A28: Transport | B28: =COUNTIF(Itinerari!$E$2:$E$236,"*"&A28&"*") -> 4
A29: Altres | B29: =COUNTIF(Itinerari!$E$2:$E$236,"*"&A29&"*") -> 8
A31: Nota: la columna "Visitat" a la pestanya Itinerari està en blanc — escriu-hi una "X" manualment als llocs que vagis visitant; el recompte d'aquí s'actualitza sol.
